flask_sqlservice.py
Flask_SQLService-0.1.0.dist-info/DESCRIPTION.rst
Flask_SQLService-0.1.0.dist-info/METADATA
Flask_SQLService-0.1.0.dist-info/RECORD
Flask_SQLService-0.1.0.dist-info/WHEEL
Flask_SQLService-0.1.0.dist-info/metadata.json
Flask_SQLService-0.1.0.dist-info/top_level.txt
