Metadata-Version: 2.0
Name: Flask-SQLService
Version: 0.1.0
Summary: Flask extension for sqlservice
Home-page: https://github.com/robinandeer/flask-sqlservice
Author: Robin Andeer
Author-email: robin.andeer@gmail.com
License: MIT
Keywords: flask sqlservice sqlalchemy databases
Platform: UNKNOWN
Classifier: Development Status :: 4 - Beta
Classifier: Environment :: Web Environment
Classifier: Intended Audience :: Developers
Classifier: Framework :: Flask
Classifier: Programming Language :: Python
Classifier: License :: OSI Approved :: MIT License
Requires-Dist: Flask
Requires-Dist: sqlservice
